authfi/__init__.py
authfi/api.py
authfi/utils.py
authfi_api-0.0.3.dist-info/licenses/LICENSE
authfi_api-0.0.3.dist-info/METADATA
authfi_api-0.0.3.dist-info/WHEEL
authfi_api-0.0.3.dist-info/top_level.txt
authfi_api-0.0.3.dist-info/RECORD
