Metadata-Version: 2.4
Name: authfi-api
Version: 0.0.3
Summary: Python wrapper for Authentrend AuthFi WebAuthn/FIDO2 API
Home-page: https://github.com/chumicat/authfi-api
Author: chumicat
Author-email: chumicat <russelltseng@gmail.com>
License-Expression: MIT
Project-URL: Homepage, https://github.com/chumicat/authfi-api
Project-URL: Repository, https://github.com/chumicat/authfi-api
Project-URL: Issues, https://github.com/chumicat/authfi-api/issues
Project-URL: Documentation, https://github.com/chumicat/authfi-api#readme
Keywords: webauthn,fido2,authentication,authfi,authentrend,security
Classifier: Development Status :: 4 - Beta
Classifier: Intended Audience :: Developers
Classifier: Topic :: Software Development :: Libraries :: Python Modules
Classifier: Topic :: Security :: Cryptography
Classifier: Programming Language :: Python :: 3
Classifier: Programming Language :: Python :: 3.7
Classifier: Programming Language :: Python :: 3.8
Classifier: Programming Language :: Python :: 3.9
Classifier: Programming Language :: Python :: 3.10
Classifier: Programming Language :: Python :: 3.11
Classifier: Programming Language :: Python :: 3.12
Classifier: Programming Language :: Python :: 3.13
Classifier: Programming Language :: Python :: 3.14
Requires-Python: >=3.7
License-File: LICENSE
Requires-Dist: fido2>=1.1.0
Requires-Dist: pydantic>=2.0.0
Requires-Dist: requests>=2.25.0
Dynamic: author
Dynamic: home-page
Dynamic: license-file
Dynamic: requires-python
